MANIFEST.in
README.rst
setup.py
html_jumping/__init__.py
html_jumping.egg-info/PKG-INFO
html_jumping.egg-info/SOURCES.txt
html_jumping.egg-info/dependency_links.txt
html_jumping.egg-info/requires.txt
html_jumping.egg-info/top_level.txt
tests/__init__.py
tests/test_html_jumping.py