Metadata-Version: 1.0
Name: html-jumping
Version: 0.2.3
Summary: Allows to get an HTML, coming from several previous URLs. Sometimes this is needed to get webpages that requires cookies or a HTTP referrer to get a certain page.
Home-page: https://github.com/dperezrada/html-jumping
Author: Daniel Perez Rada
Author-email: dperezrada@gmail.com
License: GNU Public License v3.0
Keywords: html_jumping cookies html get post form referrer
Platform: UNKNOWN
Classifier: Development Status :: 3 - Alpha
Classifier: Topic :: Utilities
Classifier: Intended Audience :: Developers
Classifier: License :: OSI Approved :: GNU General Public License (GPL)
